wwpdb/utils/markdown_wrapper/__init__.py
wwpdb/utils/markdown_wrapper/markdown_render.ini
wwpdb/utils/markdown_wrapper/render_markdown.py
wwpdb/utils/markdown_wrapper/assets/css/markdown/markdown-print.css
wwpdb/utils/markdown_wrapper/assets/css/markdown/markdown-screen.css
wwpdb/utils/markdown_wrapper/assets/css/markdown/pygments/default.css
wwpdb/utils/markdown_wrapper/assets/css/markdown/pygments/github.css
wwpdb/utils/markdown_wrapper/assets/js/mermaid/mermaid.css
wwpdb/utils/markdown_wrapper/assets/js/mermaid/mermaid.dark.css
wwpdb/utils/markdown_wrapper/assets/js/mermaid/mermaid.forest.css
wwpdb/utils/markdown_wrapper/assets/js/mermaid/mermaid.forest.print.css
wwpdb/utils/markdown_wrapper/assets/js/mermaid/mermaid.js
wwpdb/utils/markdown_wrapper/assets/js/mermaid/mermaid.js-org
wwpdb/utils/markdown_wrapper/assets/js/mermaid/mermaid.min.js
wwpdb/utils/markdown_wrapper/assets/js/mermaid/mermaid.slim.js
wwpdb/utils/markdown_wrapper/assets/js/mermaid/mermaid.slim.min.js
wwpdb/utils/markdown_wrapper/assets/js/mermaid/mermaidAPI.js
wwpdb/utils/markdown_wrapper/assets/js/mermaid/mermaidAPI.min.js
wwpdb/utils/markdown_wrapper/assets/js/mermaid/mermaidAPI.slim.js
wwpdb/utils/markdown_wrapper/assets/js/mermaid/mermaidAPI.slim.min.js
wwpdb_utils_markdown_wrapper-1.0.1.dist-info/METADATA
wwpdb_utils_markdown_wrapper-1.0.1.dist-info/WHEEL
wwpdb_utils_markdown_wrapper-1.0.1.dist-info/RECORD
